Workbook

Sheet Cover
B3: CLOUD SPHERE SOLUTIONS
B4: Ecommerce Platform — SIT / UAT Test Pack
B5: Authentication • Catalogue • Cart & Discount • Checkout • Wishlist & Orders • Admin • Non-functional
B7: Storefront / shop.cloudsphere.rw (UAT)
B10: PROJECT INFORMATION / AMAKURU Y'UMUSHINGA
B11: Project | C11: Cloud Sphere Ecommerce & Services Platform
B12: Application / Module | C12: Web storefront + REST API + database (containerized)
B13: In-scope journeys | C13: Login/Register, Catalogue, Cart, Discount, Checkout (MoMo/Card), Wishlist, Orders, Admin fulfill
B14: Out of scope | C14: Native mobile apps; payment-gateway internals; live MoMo charges; production PII
B15: Governing SRS | C15: CSS-SRS-2026-001 v1.0 — use cases UC-CS-01..13
B16: Governing Inception | C16: CSS-INC-2026-001 v1.0 — milestones M1–M5, Gantt Annex A
B17: Test Phase | C17: SIT → UAT
B18: Environment | C18: UAT / staging Kubernetes cluster (seed data: SRS Appendix B)
B19: Build / Release | C19: 1.0-rc
B20: Test Lead | C20: Year 3 SPE QA lead (rotating) · Trainer: Stanley Mwizerwa
B21: Business Owner / PO | C21: Cloud Sphere Product Owner
B22: UAT window | C22: Session 1: Week 12 · Session 2: Week 16 · Sign-off: Milestone 5
B23: Document ID / Version | C23: CSS-UAT-2026-001 · v1.0 · 20 September 2026
B26: HOW TO USE / UBURYO BWO GUKORESHA
B27: 1. Confirm entry criteria | C27: SRS baselined, Inception accepted, smoke test (home + /health) green, Appendix B seed loaded. Do not start if smoke fails.
B28: 2. Pick a test sheet | C28: Authentication, Catalogue, Cart & Discount, Checkout, Wishlist & Orders, Admin, or Non-functional.
B29: 3. Run each test case | C29: Follow Test Steps on the UAT storefront (or API notes where marked). Record Actual Result.
B30: 4. Record the outcome | C30: Status dropdown: Pass / Fail / Blocked / Not Executed. Failures get a Defect ID.
B31: 5. Watch the Dashboard | C31: Counts and pass rate update live from the Status columns.
B32: 6. Capture LO4 metrics | C32: On the Protocol sheet: task success, time on task, satisfaction 1–5.
B33: 7. Sign-off | C33: Product Owner and QA Lead complete the Dashboard sign-off (Accept / Accept with reservations / Reject).
B36: STATUS LEGEND / IBISOBANURO
B37: Pass | C37: Test executed and all expected results were observed.
B38: Fail | C38: Test executed but one or more expected results did not match.
B39: Blocked | C39: Cannot be executed because of an environment/data/dependency issue.
B40: Not Executed | C40: Default — test case has not yet been run.
B42: © Cloud Sphere Solutions / Rwanda Coding Academy — SPEDO501 capstone. Internal QA workbook. Do not distribute customer data.

Sheet UAT Protocol
B2: UAT Protocol / LO4 §2 — objectives, metrics, sign-off
B3: This sheet is the formal UAT report skeleton required by SPEDO501 LO4. Test evidence lives on the module sheets; the verdict lives here and on Dashboard.
B5: 2.1 Objectives
B6: O1 A first-time shopper can register, browse, and complete a successful MoMo checkout unaided.
B7: O2 Discount SAVE2026 and the qty≥5 / free-shipping decision table behave as SRS Appendix A.
B8: O3 MoMo timeout never leaves an order Paid (FR-PAY-03 / Chapter 1 missed-requirement scenario).
B9: O4 An operations user can publish a product and ship a Paid order from the quick-start guide alone.
B10: O5 IDOR: customer A cannot open customer B’s order.
B12: 2.2 Metrics (complete during sessions)
B13: Task (maps to objective) | C13: Participant | D13: Success Y/N | E13: Time on task (min) | F13: Satisfaction 1–5 | G13: Notes
B14: O1 Browse → register → MoMo success checkout
B15: O2 Apply SAVE2026 on 5× USB-C-01; Gold free shipping
B16: O3 Force MoMo timeout; confirm not Paid
B17: O4 Admin publish SKU + ship Paid order
B18: O5 Customer A opens Customer B order URL
B20: Task success rate | C20: =IF(COUNTA(D14:D18)=0,"",COUNTIF(D14:D18,"Y")/COUNTA(D14:D18))
B21: Average satisfaction | C21: =IF(COUNT(F14:F18)=0,"",AVERAGE(F14:F18))
B22: Defects found in UAT (count of Fail on Dashboard) | C22: =Dashboard!C11
B24: 2.3 Participants (representative users, not only developers)
B25: Name | C25: Role | D25: Session 1 / 2 | E25: Trained on quick-start?
C26: Shopper (Customer A) | D26: 1
C27: Shopper (Gold / Customer B) | D27: 1
C28: Cloud Sphere Admin / ops | D28: 1+2
C29: Product Owner | D29: 2 (sign-off)
C30: QA Lead | D30: 1+2 | E30: n/a
B33: 2.5–2.6 Verdict
B34: Overall verdict
B35: Reservations / conditions for go-live

Sheet Dashboard
B2: UAT Dashboard / Ipimo ry'ibyageragejwe
B3: Live counts of Pass / Fail / Blocked / Not Executed across all test sheets. Do not type in the count cells.
B5: Module | C5: Pass | D5: Fail | E5: Blocked | F5: Not Executed | G5: Total | H5: Pass rate
B6: Authentication | C6: ='Authentication'!D4 | D6: ='Authentication'!F4 | E6: ='Authentication'!H4 | F6: ='Authentication'!J4 | G6: ='Authentication'!B4 | H6: =IF(G6=0,0,C6/G6)
B7: Catalogue | C7: ='Catalogue'!D4 | D7: ='Catalogue'!F4 | E7: ='Catalogue'!H4 | F7: ='Catalogue'!J4 | G7: ='Catalogue'!B4 | H7: =IF(G7=0,0,C7/G7)
B8: Cart & Discount | C8: ='Cart & Discount'!D4 | D8: ='Cart & Discount'!F4 | E8: ='Cart & Discount'!H4 | F8: ='Cart & Discount'!J4 | G8: ='Cart & Discount'!B4 | H8: =IF(G8=0,0,C8/G8)
B9: Checkout | C9: ='Checkout'!D4 | D9: ='Checkout'!F4 | E9: ='Checkout'!H4 | F9: ='Checkout'!J4 | G9: ='Checkout'!B4 | H9: =IF(G9=0,0,C9/G9)
B10: Wishlist & Orders | C10: ='Wishlist & Orders'!D4 | D10: ='Wishlist & Orders'!F4 | E10: ='Wishlist & Orders'!H4 | F10: ='Wishlist & Orders'!J4 | G10: ='Wishlist & Orders'!B4 | H10: =IF(G10=0,0,C10/G10)
B11: Admin | C11: ='Admin'!D4 | D11: ='Admin'!F4 | E11: ='Admin'!H4 | F11: ='Admin'!J4 | G11: ='Admin'!B4 | H11: =IF(G11=0,0,C11/G11)
B12: Non-functional | C12: ='Non-functional'!D4 | D12: ='Non-functional'!F4 | E12: ='Non-functional'!H4 | F12: ='Non-functional'!J4 | G12: ='Non-functional'!B4 | H12: =IF(G12=0,0,C12/G12)
B13: OVERALL | C13: =SUM(C6:C12) | D13: =SUM(D6:D12) | E13: =SUM(E6:E12) | F13: =SUM(F6:F12) | G13: =SUM(G6:G12) | H13: =IF(G13=0,0,C13/G13)
B32: UAT SIGN-OFF / KWEMEZA
B33: Role | C33: Name | D33: Decision | E33: Signature | F33: Date
B34: Product Owner, Cloud Sphere Solutions
B35: QA Lead
B36: Trainer / Technical authority
B38: Sign-off authorises (or refuses) release to the integrated summative demo / production-like cluster. It is not a developer “done”.

Sheet Authentication
A2: Authentication / Kwinjira
A3: Welcome, PIN/password, lock-out, registration, session and logging. Maps to UC-CS-03/04 and FR-AUTH-*.
A4: Total | B4: =COUNTA(B6:B17) | C4: Pass | D4: =COUNTIF(K6:K17,"Pass") | E4: Fail | F4: =COUNTIF(K6:K17,"Fail") | G4: Blocked | H4: =COUNTIF(K6:K17,"Blocked") | I4: Not Executed | J4: =COUNTIF(K6:K17,"Not Executed") | K4: Pass rate | L4: =IF(B4=0,0,D4/B4)
A5: # | B5: Test ID | C5: Module | D5: Sub-module | E5: Test Case Title | F5: Pre-conditions | G5: Test Steps | H5: Expected Result | I5: Actual Result | J5: Priority | K5: Status | L5: Tester | M5: Test Date | N5: Defect ID | O5: Comments
A6: 1 | B6: AU-001 | C6: Authentication | D6: Welcome | E6: Login page loads (smoke) | F6: UAT cluster healthy. | G6: Open /login. | H6: Email and password fields and Sign in button are visible; labelled for assistive tech. | J6: Critical | K6: Not Executed
A7: 2 | B7: AU-002 | C7: Authentication | D7: Happy path | E7: Registered customer logs in | F7: demo@cloudsphere.rw exists (Appendix B). | G7: 1. Open /login. 2. Enter demo email + correct password. 3. Submit. | H7: Redirect to previous page or home; session cookie set; user menu shows email. | J7: Critical | K7: Not Executed | O7: UC-CS-04 main flow
A8: 3 | B8: AU-003 | C8: Authentication | D8: Invalid password | E8: Wrong password — generic error | F8: demo@cloudsphere.rw exists. | G8: Submit correct email + wrong password. | H8: Generic error; no stack trace; does not say “password incorrect” vs “email unknown”. | J8: Critical | K8: Not Executed | O8: UC-CS-04 3a / FND-CSS-021 anti-pattern forbidden
A9: 4 | B9: AU-004 | C9: Authentication | D9: Unknown email | E9: Unknown email — same generic error | F9: Email not in store. | G9: Submit nobody@cloudsphere.rw + any password. | H9: Same generic error as AU-003 (no user enumeration). | J9: High | K9: Not Executed
A10: 5 | B10: AU-005 | C10: Authentication | D10: Lock-out | E10: Account locks after 3 wrong passwords | F10: Fresh failed-attempt counter. | G10: Submit wrong password three times in a row for demo@. | H10: Third attempt locks 30 min; security email requested; further logins denied. | J10: Critical | K10: Not Executed
A11: 6 | B11: AU-006 | C11: Authentication | D11: Locked user | E11: Already-locked account cannot log in | F11: locked@cloudsphere.rw is locked. | G11: Submit correct password for locked user. | H11: Denied; message does not confirm the email exists. | J11: High | K11: Not Executed
A12: 7 | B12: AU-007 | C12: Authentication | D12: Blank password | E12: Blank password client validation | F12: Login form. | G12: Fill email, leave password empty, click Sign in. | H12: “password is required” shown (query-by-label behaviour). | J12: Medium | K12: Not Executed | O12: SRS FR-AUTH-08 / RTL example
A13: 8 | B13: AU-008 | C13: Authentication | D13: Register | E13: Register — happy path | F13: New unique email. | G13: Complete register with valid 07X phone and 8+ char password; submit. | H13: Account created; user signed in; welcome email requested. | J13: High | K13: Not Executed
A14: 9 | B14: AU-009 | C14: Authentication | D14: Register | E14: Register — duplicate email | F14: demo@ already exists. | G14: Register with demo@cloudsphere.rw. | H14: Rejected; offer Log in; no second account. | J14: High | K14: Not Executed
A15: 10 | B15: AU-010 | C15: Authentication | D15: Logging | E15: Password never appears in logs | F15: Access to API logs. | G15: Run AU-002; inspect logs for the password string. | H15: Logs show inputLen only; password absent. | J15: High | K15: Not Executed | O15: SEC-08
A16: 11 | B16: AU-011 | C16: Authentication | D16: Logout | E16: Logout invalidates session | F16: Logged in. | G16: Logout; press Back; hit /account. | H16: Redirected to login; old cookie unusable. | J16: High | K16: Not Executed
A17: 12 | B17: AU-012 | C17: Authentication | D17: Phone BVA | E17: Register rejects 9-digit phone | F17: Registration form. | G17: Enter 078123456 (9 digits) as phone. | H17: Rejected (Rwandan 07X 10-digit rule). | J17: Medium | K17: Not Executed | O17: Chapter 1 Exercise 30

Sheet Catalogue
A2: Catalogue / Urutonde rw'ibicuruzwa
A3: Smoke, search, published vs hidden, stock badges and product API. Maps to UC-CS-01/02.
A4: Total | B4: =COUNTA(B6:B15) | C4: Pass | D4: =COUNTIF(K6:K15,"Pass") | E4: Fail | F4: =COUNTIF(K6:K15,"Fail") | G4: Blocked | H4: =COUNTIF(K6:K15,"Blocked") | I4: Not Executed | J4: =COUNTIF(K6:K15,"Not Executed") | K4: Pass rate | L4: =IF(B4=0,0,D4/B4)
A5: # | B5: Test ID | C5: Module | D5: Sub-module | E5: Test Case Title | F5: Pre-conditions | G5: Test Steps | H5: Expected Result | I5: Actual Result | J5: Priority | K5: Status | L5: Tester | M5: Test Date | N5: Defect ID | O5: Comments
A6: 1 | B6: CAT-001 | C6: Catalogue | D6: Smoke | E6: Home page loads | F6: UAT up. | G6: GET / | H6: Home renders with at least the published catalogue region. If this fails, stop the cycle. | J6: Critical | K6: Not Executed | O6: STLC Phase 4 exit / FR-CAT-04
A7: 2 | B7: CAT-002 | C7: Catalogue | D7: List | E7: Published products listed with RWF prices | F7: USB-C-01 seeded. | G7: Open catalogue. | H7: USB-C-01 visible; price 15,000 RWF integer. | J7: High | K7: Not Executed
A8: 3 | B8: CAT-003 | C8: Catalogue | D8: Search | E8: Search by name — hit | F8: USB-C-01 published. | G8: Search “USB”. | H8: USB-C-01 in results. | J8: High | K8: Not Executed
A9: 4 | B9: CAT-004 | C9: Catalogue | D9: Search | E9: Search — zero hits empty state | F9: None. | G9: Search “zzzz-no-sku”. | H9: “No products match your search.” not a blank page. | J9: Medium | K9: Not Executed
A10: 5 | B10: CAT-005 | C10: Catalogue | D10: Unpublished | E10: Unpublished SKU hidden from guest | F10: HIDDEN-01 unpublished. | G10: Search HIDDEN-01 and open /products/HIDDEN-01. | H10: Not in search; detail is 404. | J10: High | K10: Not Executed
A11: 6 | B11: CAT-006 | C11: Catalogue | D11: Detail | E11: Product detail in-stock | F11: USB-C-01 stockQty=20. | G11: Open product. | H11: Add to cart enabled; stock badge in stock. | J11: High | K11: Not Executed
A12: 7 | B12: CAT-007 | C12: Catalogue | D12: Detail | E12: Out-of-stock disables add | F12: OOS-01 stockQty=0. | G12: Open OOS-01. | H12: Add to cart and wishlist disabled. | J12: High | K12: Not Executed
A13: 8 | B13: CAT-008 | C13: Catalogue | D13: API | E13: Unknown product id returns 404 | F13: API reachable. | G13: GET /api/products/does-not-exist | H13: HTTP 404 JSON; no stack trace. | J13: High | K13: Not Executed
A14: 9 | B14: CAT-009 | C14: Catalogue | D14: Health | E14: /health ready for smoke | F14: Cluster up. | G14: GET /health or /api/health | H14: 200; does not dump library versions. | J14: High | K14: Not Executed
A15: 10 | B15: CAT-010 | C15: Catalogue | D15: Pagination | E15: Catalogue paginates at 20 | F15: >20 published products (seed extra if needed). | G15: Open page 1 then 2. | H15: 20 items page 1; remainder on page 2. | J15: Medium | K15: Not Executed

Sheet Cart & Discount
A2: Cart & Discount / Agatebo n'igabanuka
A3: Cart merge, EP/BVA on discount codes, 10% qty rule, free-shipping decision table. Maps to UC-CS-05/06.
A4: Total | B4: =COUNTA(B6:B19) | C4: Pass | D4: =COUNTIF(K6:K19,"Pass") | E4: Fail | F4: =COUNTIF(K6:K19,"Fail") | G4: Blocked | H4: =COUNTIF(K6:K19,"Blocked") | I4: Not Executed | J4: =COUNTIF(K6:K19,"Not Executed") | K4: Pass rate | L4: =IF(B4=0,0,D4/B4)
A5: # | B5: Test ID | C5: Module | D5: Sub-module | E5: Test Case Title | F5: Pre-conditions | G5: Test Steps | H5: Expected Result | I5: Actual Result | J5: Priority | K5: Status | L5: Tester | M5: Test Date | N5: Defect ID | O5: Comments
A6: 1 | B6: CART-001 | C6: Cart | D6: Add | E6: Add in-stock item to cart | F6: USB-C-01 in stock. | G6: Add qty 1 from detail. | H6: Cart shows 1 × USB-C-01; confirmation. | J6: Critical | K6: Not Executed
A7: 2 | B7: CART-002 | C7: Cart | D7: Qty | E7: Qty greater than stock rejected | F7: stockQty=20. | G7: Add qty 21. | H7: Rejected; remaining 20 shown; cart unchanged. | J7: High | K7: Not Executed
A8: 3 | B8: CART-003 | C8: Cart | D8: Merge | E8: Anonymous cart merges on login | F8: Guest cart has USB-C-01. | G8: Log in as demo@. | H8: Cart retained; no duplicate SKU lines. | J8: High | K8: Not Executed
A9: 4 | B9: CART-004 | C9: Cart | D9: Totals | E9: Line totals = qty × unit price | F9: 2 × 15,000 in cart. | G9: Open cart. | H9: Subtotal 30,000 RWF before shipping/discount. | J9: High | K9: Not Executed
A10: 5 | B10: CART-005 | C10: Discount | D10: EP P1 | E10: Code length 4 rejected | F10: Cart non-empty. | G10: Apply AB12. | H10: “code must be 5–10 characters”; totals unchanged. | J10: High | K10: Not Executed | O10: Chapter 1 §7.1 P1
A11: 6 | B11: CART-006 | C11: Discount | D11: EP P2 | E11: Valid length SAVE2026 accepted for further check | F11: Active code SAVE2026. | G11: Apply SAVE2026. | H11: Accepted or applied per remaining rules; not a length error. | J11: High | K11: Not Executed
A12: 7 | B12: CART-007 | C12: Discount | D12: EP P3 | E12: Code length 18 rejected | F12: Cart non-empty. | G12: Apply SAVE2026SUMMERBIG. | H12: Length error; totals unchanged. | J12: High | K12: Not Executed
A13: 8 | B13: CART-008 | C13: Discount | D13: EP P4 | E13: Non-alphanumeric code rejected | F13: Cart non-empty. | G13: Apply SAVE-25!. | H13: “code contains invalid characters”. | J13: High | K13: Not Executed
A14: 9 | B14: CART-009 | C14: Discount | D14: BVA | E14: Length 5 accepted / 11 rejected | F14: A 5-char active code exists or use SAVE2 if seeded. | G14: Try 5-char then 11-char. | H14: 5 accepted structurally; 11 rejected. | J14: High | K14: Not Executed
A15: 10 | B15: CART-010 | C15: Discount | D15: Unknown | E15: Unknown code does not reduce price | F15: Cart 30,000. | G15: Apply FAKE99. | H15: “code is not valid”; total still 30,000 + shipping. | J15: High | K15: Not Executed
A16: 11 | B16: CART-011 | C16: Discount | D16: Qty rule | E16: 5 items get 10% off (TDD) | F16: USB-C-01 stock ≥5. | G16: Qty 5; no conflicting code that stacks twice. | H16: Item subtotal 5×15000×0.9 = 67,500. | J16: High | K16: Not Executed | O16: FR-DISC-04
A17: 12 | B17: CART-012 | C17: Discount | D17: Qty rule | E17: 4 items get 0% off | F17: stock ≥4. | G17: Qty 4. | H17: Subtotal 60,000; no 10%. | J17: High | K17: Not Executed
A18: 13 | B18: CART-013 | C18: Shipping | D18: Decision table | E18: Standard under 50k pays 2,000 shipping | F18: demo@ Standard; subtotal 30,000. | G18: Open checkout invoice. | H18: Shipping 2,000 RWF. | J18: High | K18: Not Executed
A19: 14 | B19: CART-014 | C19: Shipping | D19: Decision table | E19: Gold under 50k ships free | F19: gold@cloudsphere.rw; subtotal 30,000. | G19: Open checkout invoice as Gold. | H19: Shipping 0 RWF. | J19: High | K19: Not Executed | O19: Appendix A row 3

Sheet Checkout
A2: Checkout / Kwishyura
A3: Place order (Airline Book-flight analogue), MoMo/Card, timeout-after-Paid, idempotency. Maps to UC-CS-07/08.
A4: Total | B4: =COUNTA(B6:B19) | C4: Pass | D4: =COUNTIF(K6:K19,"Pass") | E4: Fail | F4: =COUNTIF(K6:K19,"Fail") | G4: Blocked | H4: =COUNTIF(K6:K19,"Blocked") | I4: Not Executed | J4: =COUNTIF(K6:K19,"Not Executed") | K4: Pass rate | L4: =IF(B4=0,0,D4/B4)
A5: # | B5: Test ID | C5: Module | D5: Sub-module | E5: Test Case Title | F5: Pre-conditions | G5: Test Steps | H5: Expected Result | I5: Actual Result | J5: Priority | K5: Status | L5: Tester | M5: Test Date | N5: Defect ID | O5: Comments
A6: 1 | B6: CO-001 | C6: Checkout | D6: Gate | E6: Checkout requires login | F6: Guest cart non-empty. | G6: Click Checkout. | H6: Include::LOGIN; after success return to checkout. | J6: Critical | K6: Not Executed
A7: 2 | B7: CO-002 | C7: Checkout | D7: Empty | E7: Empty cart cannot place order | F7: Logged in, empty cart. | G7: POST place order or click Pay. | H7: Rejected; no Order row. | J7: High | K7: Not Executed
A8: 3 | B8: CO-003 | C8: Checkout | D8: Happy MoMo | E8: MoMo success → Paid + order number | F8: demo@ cart valid; adapter set to success. | G8: Checkout → MTN_MOMO → confirm. | H8: “transaction has been successful”; Order=Paid; notification requested; stock committed. | J8: Critical | K8: Not Executed | O8: UC-CS-07 main / Airline post-condition analogue
A9: 4 | B9: CO-004 | C9: Checkout | D9: Happy Card | E9: Card success → Paid | F9: Adapter success. | G9: Checkout → CARD → confirm. | H9: Paid; PAN not stored (inspect DB/payload). | J9: High | K9: Not Executed
A10: 5 | B10: CO-005 | C10: Checkout | D10: Decline | E10: Declined payment — customer not charged | F10: Adapter decline. | G10: Confirm pay. | H10: Error displayed; no Paid order; cart reservation released or still Placed unpaid; money=0. | J10: Critical | K10: Not Executed
A11: 6 | B11: CO-006 | C11: Checkout | D11: Cancel | E11: Customer cancels before pay | F11: On invoice step. | G11: Click Cancel and confirm “are you sure?”. | H11: Back to cart; no order; no charge. | J11: High | K11: Not Executed
A12: 7 | B12: CO-007 | C12: Checkout | D12: Idempotency | E12: Double submit does not double charge | F12: Adapter success. | G12: Double-click Place order / replay Idempotency-Key. | H12: One Order, one charge. | J12: High | K12: Not Executed
A13: 8 | B13: CO-008 | C13: Payment | D13: Timeout | E13: 45s no callback → PaymentTimedOut not Paid | F13: Adapter timeout mode. | G13: Start MoMo pay; wait past 45s. | H13: State PaymentTimedOut; customer not charged; message to retry. | J13: Critical | K13: Not Executed | O13: FR-PAY-02
A14: 9 | B14: CO-009 | C14: Payment | D14: Timeout after Paid | E14: Late timeout after provisional Paid is corrected | F14: Adapter: success then timeout signal (Chapter 1 scenario). | G14: Complete pay; inject timeout/cancel from stub. | H14: Order leaves Paid → PaymentTimedOut; ops alert; stock/money consistent. | J14: Critical | K14: Not Executed | O14: FR-PAY-03 missed-requirement
A15: 10 | B15: CO-010 | C15: Payment | D15: Duplicate webhook | E15: Duplicate success callback is idempotent | F15: Already Paid. | G15: Replay gateway success webhook. | H15: Still one Paid order; no second capture. | J15: High | K15: Not Executed
A16: 11 | B16: CO-011 | C16: Checkout | D16: 5 minute abandon | E16: Abandoned checkout cancels reservation | F16: On invoice, do not pay. | G16: Wait 5+ minutes (or trigger job). | H16: Reservation cancelled; stock available again. | J16: Medium | K16: Not Executed
A17: 12 | B17: CO-012 | C17: Checkout | D17: OOS race | E17: Item goes OOS between cart and pay | F17: stockQty=1; two sessions. | G17: Both attempt checkout. | H17: Only one Paid; other sees stock error; no oversell. | J17: High | K17: Not Executed
A18: 13 | B18: CO-013 | C18: Checkout | D18: Invoice | E18: Invoice shows subtotal, discount, shipping, total | F18: Cart with SAVE2026 and shipping rule. | G18: Reach step 5. | H18: Four figures visible in RWF; match FR-CART-04. | J18: High | K18: Not Executed
A19: 14 | B19: CO-014 | C19: Checkout | D19: Change method | E19: Switch MoMo to Card before confirm | F19: On payment step. | G19: Change method; confirm Card success. | H19: Paid via CARD; no MoMo charge. | J19: Medium | K19: Not Executed

Sheet Wishlist & Orders
A2: Wishlist & Orders / Ibyifuzo n'ibitumwa
A3: REQ-WL-01..06 including persistence, IDOR, legal and illegal order transitions. Maps to UC-CS-09/10/12.
A4: Total | B4: =COUNTA(B6:B19) | C4: Pass | D4: =COUNTIF(K6:K19,"Pass") | E4: Fail | F4: =COUNTIF(K6:K19,"Fail") | G4: Blocked | H4: =COUNTIF(K6:K19,"Blocked") | I4: Not Executed | J4: =COUNTIF(K6:K19,"Not Executed") | K4: Pass rate | L4: =IF(B4=0,0,D4/B4)
A5: # | B5: Test ID | C5: Module | D5: Sub-module | E5: Test Case Title | F5: Pre-conditions | G5: Test Steps | H5: Expected Result | I5: Actual Result | J5: Priority | K5: Status | L5: Tester | M5: Test Date | N5: Defect ID | O5: Comments
A6: 1 | B6: WO-001 | C6: Wishlist | D6: Add | E6: Add in-stock item (REQ-WL-01) | F6: Logged in demo@; USB-C-01 in stock. | G6: Click Save to wishlist. | H6: Item on wishlist page. | J6: High | K6: Not Executed
A7: 2 | B7: WO-002 | C7: Wishlist | D7: OOS | E7: Cannot add out-of-stock (REQ-WL-02) | F7: OOS-01. | G7: Save to wishlist. | H7: Rejected with message. | J7: High | K7: Not Executed
A8: 3 | B8: WO-003 | C8: Wishlist | D8: Auth | E8: Guest wishlist redirects to login (REQ-WL-03) | F8: Logged out. | G8: Open /wishlist. | H8: Redirect login; after login return to wishlist. | J8: High | K8: Not Executed
A9: 4 | B9: WO-004 | C9: Wishlist | D9: Icon | E9: Icon updates without full refresh (REQ-WL-04) | F9: Logged in on product page. | G9: Add to wishlist; watch icon. | H9: Icon/count updates immediately (DEF-118 class). | J9: High | K9: Not Executed
A10: 5 | B10: WO-005 | C10: Wishlist | D10: Cart | E10: Move wishlist item to cart (REQ-WL-05) | F10: Item on wishlist. | G10: Move to cart. | H10: Cart has the SKU; wishlist still has it unless confirmed remove. | J10: Medium | K10: Not Executed
A11: 6 | B11: WO-006 | C11: Wishlist | D11: Persist | E11: Wishlist persists across sessions (REQ-WL-06) | F11: Item saved. | G11: Logout, login, open wishlist. | H11: Item still present. This case MUST exist on the RTM. | J11: Critical | K11: Not Executed | O11: Lecture REQ-WL-06 untested trap
A12: 7 | B12: WO-007 | C12: Wishlist | D12: Unpublished | E12: Unpublished product cannot stay actionable | F12: Admin unpublishes a wishlisted SKU. | G12: Open wishlist. | H12: Item marked unavailable; move-to-cart disabled. | J12: Medium | K12: Not Executed
A13: 8 | B13: WO-008 | C13: Orders | D13: Track | E13: Customer sees own Paid order | F13: CO-003 succeeded. | G13: Open My orders. | H13: Order number, Paid, lines visible. | J13: High | K13: Not Executed
A14: 9 | B14: WO-009 | C14: Orders | D14: IDOR | E14: Customer A cannot read Customer B order | F14: Two customers with orders. | G14: As A, GET /api/orders/{B.id} and open B’s URL. | H14: 404 (not 403 with body leak). | J14: Critical | K14: Not Executed | O14: SEC-02
A15: 10 | B15: WO-010 | C15: Orders | D15: State | E15: Legal path Placed→Paid→Shipped→Delivered | F15: Admin user. | G15: Fulfill a Paid order to Delivered. | H15: Each transition succeeds; notifications requested. | J15: High | K15: Not Executed
A16: 11 | B16: WO-011 | C16: Orders | D16: Illegal | E16: Reject Delivered → Placed | F16: Delivered order. | G16: PATCH state=Placed. | H16: HTTP 409; state unchanged. | J16: High | K16: Not Executed | O16: Exercise 33 analogue
A17: 12 | B17: WO-012 | C17: Orders | D17: Illegal | E17: Reject Paid → Placed | F17: Paid order. | G17: PATCH state=Placed. | H17: 409; no payment reversal in this version. | J17: High | K17: Not Executed
A18: 13 | B18: WO-013 | C18: Orders | D18: Illegal | E18: Reject ship of unpaid Placed order | F18: Placed unpaid. | G18: Admin Mark shipped. | H18: Rejected; stays Placed. | J18: High | K18: Not Executed
A19: 14 | B19: WO-014 | C19: Orders | D19: Unknown | E19: Unknown order id is 404 | F19: Logged in. | G19: Open /orders/no-such-id. | H19: 404. | J19: Medium | K19: Not Executed

Sheet Admin
A2: Admin / Ubuyobozi
A3: Authorisation, publish/unpublish, stock, ship/deliver, quick-start validation task (LO4).
A4: Total | B4: =COUNTA(B6:B13) | C4: Pass | D4: =COUNTIF(K6:K13,"Pass") | E4: Fail | F4: =COUNTIF(K6:K13,"Fail") | G4: Blocked | H4: =COUNTIF(K6:K13,"Blocked") | I4: Not Executed | J4: =COUNTIF(K6:K13,"Not Executed") | K4: Pass rate | L4: =IF(B4=0,0,D4/B4)
A5: # | B5: Test ID | C5: Module | D5: Sub-module | E5: Test Case Title | F5: Pre-conditions | G5: Test Steps | H5: Expected Result | I5: Actual Result | J5: Priority | K5: Status | L5: Tester | M5: Test Date | N5: Defect ID | O5: Comments
A6: 1 | B6: AD-001 | C6: Admin | D6: Authz | E6: Non-admin cannot open admin console | F6: demo@ customer. | G6: GET /admin and POST /api/admin/products. | H6: 403 / redirect; no product created. | J6: Critical | K6: Not Executed
A7: 2 | B7: AD-002 | C7: Admin | D7: Publish | E7: Admin publishes unique SKU | F7: ops@cloudsphere.rw. | G7: Create SKU CAP-01 published price 8,000 stock 5. | H7: Appears on storefront within 5 s. | J7: High | K7: Not Executed
A8: 3 | B8: AD-003 | C8: Admin | D8: Duplicate | E8: Duplicate SKU rejected | F8: USB-C-01 exists. | G8: Create another USB-C-01. | H8: Validation error; original unchanged. | J8: High | K8: Not Executed
A9: 4 | B9: AD-004 | C9: Admin | D9: Stock | E9: Negative stock rejected | F9: Admin on USB-C-01. | G9: Set stockQty=-1. | H9: Rejected. | J9: High | K9: Not Executed
A10: 5 | B10: AD-005 | C10: Admin | D10: Unpublish | E10: Unpublish hides from search | F10: CAP-01 published. | G10: Unpublish. | H10: Guest search 404/hidden (CAT-005 behaviour). | J10: High | K10: Not Executed
A11: 6 | B11: AD-006 | C11: Admin | D11: Ship | E11: Mark Paid order shipped with tracking | F11: A Paid order. | G11: Enter tracking; Mark shipped. | H11: State=Shipped; customer notified. | J11: High | K11: Not Executed
A12: 7 | B12: AD-007 | C12: Admin | D12: Deliver | E12: Mark Shipped order delivered | F12: Shipped order. | G12: Mark delivered. | H12: State=Delivered. | J12: High | K12: Not Executed
A13: 8 | B13: AD-008 | C13: Admin | D13: Quick-start | E13: Ops user completes publish+ship using only quick-start | F13: UAT Protocol O4 participant is not the feature’s developer. | G13: Hand only the quick-start guide; time the task. | H13: Task success without developer help; time recorded on Protocol sheet. | J13: High | K13: Not Executed | O13: LO4 UAT objective — validation not verification

Sheet Non-functional
A2: Non-functional / Imikorere n'umutekano
A3: Performance, pipeline, OWASP checks, observability and accessibility. Maps to NFR-* / SEC-* / FR-DEV-* / FR-OBS-*.
A4: Total | B4: =COUNTA(B6:B15) | C4: Pass | D4: =COUNTIF(K6:K15,"Pass") | E4: Fail | F4: =COUNTIF(K6:K15,"Fail") | G4: Blocked | H4: =COUNTIF(K6:K15,"Blocked") | I4: Not Executed | J4: =COUNTIF(K6:K15,"Not Executed") | K4: Pass rate | L4: =IF(B4=0,0,D4/B4)
A5: # | B5: Test ID | C5: Module | D5: Sub-module | E5: Test Case Title | F5: Pre-conditions | G5: Test Steps | H5: Expected Result | I5: Actual Result | J5: Priority | K5: Status | L5: Tester | M5: Test Date | N5: Defect ID | O5: Comments
A6: 1 | B6: NF-001 | C6: Non-functional | D6: Perf | E6: Login p95 ≤ 500 ms at 100 concurrent | F6: JMeter/Gatling script; UAT cluster. | G6: Ramp 100 users login. | H6: p95 ≤ 500 ms; error-rate < 1%. | J6: High | K6: Not Executed | O6: NFR-PERF-01
A7: 2 | B7: NF-002 | C7: Non-functional | D7: Load | E7: 50 concurrent checkout 60 s error-rate < 1% | F7: Lab 4 script. | G7: 50 users 60 s against checkout API. | H7: Error-rate < 1%; report attached. | J7: High | K7: Not Executed
A8: 3 | B8: NF-003 | C8: Non-functional | D8: Stress | E8: 200 concurrent fails gracefully | F8: Stress script. | G8: 200 concurrent checkout. | H8: No paid-without-stock; no HTML 500 stack traces. | J8: Medium | K8: Not Executed
A9: 4 | B9: NF-004 | C9: Non-functional | D9: Pipeline | E9: CI Test stage runs unit tests | F9: Repo with Jest/JUnit. | G9: Push a failing unit test on a branch. | H9: Pipeline red; Deploy did not run. | J9: High | K9: Not Executed | O9: FR-DEV-03
A10: 5 | B10: NF-005 | C10: Non-functional | D10: Security | E10: No stack traces on 500 | F10: Force an API error (invalid UUID storm). | G10: Observe UI and JSON. | H10: Generic error + trace_id; no stack. | J10: High | K10: Not Executed
A11: 6 | B11: NF-006 | C11: Non-functional | D11: Dependencies | E11: npm audit / Maven CVE check in pipeline | F11: Test stage configured. | G11: Open pipeline log. | H11: Audit step present; High CVEs triaged. | J11: Medium | K11: Not Executed | O11: SEC-05
A12: 7 | B12: NF-007 | C12: Non-functional | D12: Logs | E12: JSON logs include trace_id | F12: Hit /api/products. | G12: Read API stdout / Loki. | H12: One JSON object per line with trace_id. | J12: High | K12: Not Executed
A13: 8 | B13: NF-008 | C13: Non-functional | D13: Dashboard | E13: Grafana four golden signals | F13: Lab 5 stack. | G13: Open dashboard. | H13: Latency, traffic, errors, saturation panels with live data. | J13: High | K13: Not Executed
A14: 9 | B14: NF-009 | C14: Non-functional | D14: Alert | E14: Error-rate alert delivers to channel | F14: Alert rule + webhook. | G14: Generate errors above threshold. | H14: Notification received; evidence attached. | J14: High | K14: Not Executed
A15: 10 | B15: NF-010 | C15: Non-functional | D15: A11y | E15: Checkout keyboard-only | F15: Browser, no mouse. | G15: Tab through checkout; complete with keyboard. | H15: All controls reachable; labels announced. | J15: Medium | K15: Not Executed
